seokbong_division/__init__.py
seokbong_division/division.py
seokbong_division-0.3.0.dist-info/METADATA
seokbong_division-0.3.0.dist-info/WHEEL
seokbong_division-0.3.0.dist-info/entry_points.txt
seokbong_division-0.3.0.dist-info/top_level.txt
seokbong_division-0.3.0.dist-info/RECORD
