Metadata-Version: 2.1
Name: seokbong_division
Version: 0.3.0
Summary: Default template for PDM package
Author-email: tbongkim03 <tbongkim03@gmial.com>
License: MIT
Requires-Python: >=3.9
